FltkManual/README.md
FltkManual/__init__.py
FltkManual/__main__.py
FltkManual/file.epub
FltkManual/index.html
FltkManual/css/__init__.py
FltkManual/css/annotations.css
FltkManual/css/main.css
FltkManual/css/normalize.css
FltkManual/css/popup.css
FltkManual/font/__init__.py
FltkManual/font/fontello.eot
FltkManual/font/fontello.svg
FltkManual/font/fontello.ttf
FltkManual/font/fontello.woff
FltkManual/img/__init__.py
FltkManual/img/annotator-glyph-sprite.png
FltkManual/img/annotator-icon-sprite.png
FltkManual/img/apple-touch-icon.png
FltkManual/img/cancelfullscreen.png
FltkManual/img/close.png
FltkManual/img/fullscreen.png
FltkManual/img/loader.gif
FltkManual/img/menu-icon.png
FltkManual/img/save.png
FltkManual/img/saved.png
FltkManual/img/settings-s.png
FltkManual/img/settings.png
FltkManual/img/star.png
FltkManual/js/__init__.py
FltkManual/js/epub.js
FltkManual/js/epub.min.js
FltkManual/js/epub.min.map
FltkManual/js/hooks.min.js
FltkManual/js/hooks.min.map
FltkManual/js/reader.js
FltkManual/js/reader.js.map
FltkManual/js/reader.min.js
FltkManual/js/reader.min.map
FltkManual/js/hooks/__init__.py
FltkManual/js/hooks/extensions/__init__.py
FltkManual/js/hooks/extensions/highlight.js
FltkManual/js/libs/__init__.py
FltkManual/js/libs/jquery.min.js
FltkManual/js/libs/localforage.min.js
FltkManual/js/libs/screenfull.js
FltkManual/js/libs/screenfull.min.js
FltkManual/js/libs/zip.min.js
FltkManual/js/plugins/__init__.py
FltkManual/js/plugins/hypothesis.js
FltkManual/js/plugins/search.js
fltk_manual-2024.3.2.0.dist-info/METADATA
fltk_manual-2024.3.2.0.dist-info/WHEEL
fltk_manual-2024.3.2.0.dist-info/entry_points.txt
fltk_manual-2024.3.2.0.dist-info/top_level.txt
fltk_manual-2024.3.2.0.dist-info/RECORD
